README.md
setup.cfg
setup.py
eis/__init__.py
eis/insurance/__init__.py
eis/insurance/api_client.py
eis/insurance/configuration.py
eis/insurance/exceptions.py
eis/insurance/model_utils.py
eis/insurance/rest.py
eis/insurance/api/__init__.py
eis/insurance/api/booking_funnel_versions_api.py
eis/insurance/api/booking_funnels_api.py
eis/insurance/api/commission_agreement_items_api.py
eis/insurance/api/commission_agreement_products_api.py
eis/insurance/api/commission_agreement_versions_api.py
eis/insurance/api/commission_agreements_api.py
eis/insurance/api/commission_recipients_api.py
eis/insurance/api/emil_functions_api.py
eis/insurance/api/health_check_api.py
eis/insurance/api/insured_object_types_api.py
eis/insurance/api/insured_objects_api.py
eis/insurance/api/lead_statuses_api.py
eis/insurance/api/lead_versions_api.py
eis/insurance/api/leads_api.py
eis/insurance/api/named_ranges_api.py
eis/insurance/api/partner_links_api.py
eis/insurance/api/partner_roles_api.py
eis/insurance/api/policies_api.py
eis/insurance/api/premium_formulas_api.py
eis/insurance/api/product_factors_api.py
eis/insurance/api/product_fields_api.py
eis/insurance/api/product_versions_api.py
eis/insurance/api/products_api.py
eis/insurance/api/status_transition_rules_api.py
eis/insurance/apis/__init__.py
eis/insurance/model/__init__.py
eis/insurance/model/activate_policy_request_dto.py
eis/insurance/model/activate_policy_response_class.py
eis/insurance/model/bank_transfer_dto.py
eis/insurance/model/billing_address_dto.py
eis/insurance/model/booking_funnel_class.py
eis/insurance/model/calculate_custom_premium_request_dto.py
eis/insurance/model/calculate_premium_request_dto.py
eis/insurance/model/calculate_product_fields_request_dto.py
eis/insurance/model/clone_lead_request_dto.py
eis/insurance/model/clone_product_version_request_dto.py
eis/insurance/model/commission_agreement_class.py
eis/insurance/model/commission_agreement_item_class.py
eis/insurance/model/commission_agreement_product_class.py
eis_insurance.egg-info/PKG-INFO
eis_insurance.egg-info/SOURCES.txt
eis_insurance.egg-info/dependency_links.txt
eis_insurance.egg-info/requires.txt
eis_insurance.egg-info/top_level.txt
