Metadata-Version: 2.1
Name: eis-insurance
Version: 1.85.0
Summary: EMIL InsuranceService
Home-page: UNKNOWN
Author: Contact us
Author-email: kontakt@emil.de
License: UNKNOWN
Keywords: OpenAPI,OpenAPI-Generator,EMIL InsuranceService
Platform: UNKNOWN
Requires-Python: >=3.6
